formatbr/__init__.py
formatbr/data_types/__init__.py
formatbr/data_types/text.py
formatbr-0.0.1.dist-info/METADATA
formatbr-0.0.1.dist-info/WHEEL
formatbr-0.0.1.dist-info/top_level.txt
formatbr-0.0.1.dist-info/RECORD
