Metadata-Version: 2.1
Name: formatbr
Version: 0.0.1
Summary: This module offers tools for data formatting.
Home-page: https://github.com/maxwelldeveloper7/dio_cursos/tree/main/python/tratamento_de_dados/criacao_de_pacotes/FormatBr
Author: Maxwell de Oliveira Chaves
Author-email: maxwellchaves1844@gmail.com
License: UNKNOWN
Platform: UNKNOWN
Requires-Python: >=3.8
